hootsweet/__init__.py
hootsweet/api.py
hootsweet/constants.py
hootsweet/exceptions.py
hootsweet/locale.py
hootsweet-0.7.1.dist-info/WHEEL
hootsweet-0.7.1.dist-info/METADATA
hootsweet-0.7.1.dist-info/RECORD
