Metadata-Version: 2.1
Name: hootsweet
Version: 0.7.1
Summary: A python library for the HootSuite REST API.
Keywords: hootsuite,api,social
Author: Ciaran McCormick
Author-email: ciaran@ciaranmccormick.com
Requires-Python: >=3.6,<4.0
Classifier: Development Status :: 3 - Alpha
Classifier: Intended Audience :: Developers
Classifier: Natural Language :: English
Classifier: Programming Language :: Python :: 3
Classifier: Programming Language :: Python :: 3.6
Classifier: Programming Language :: Python :: 3.7
Classifier: Programming Language :: Python :: 3.8
Classifier: Topic :: Software Development :: Libraries
Requires-Dist: cherrypy (>=18.5.0,<19.0.0)
Requires-Dist: pytz (>=2019.3,<2020.0)
Requires-Dist: requests (>=2.23,<3.0)
Requires-Dist: requests_oauthlib (>=1.3.0,<2.0.0)
